{
  "number": 220,
  "buttondown_id": "em_14jx9kdmth92j9wtsk014y222e",
  "subject": "Weekly Thing #220 / Ukraine DAO, Nouns, Icebergs",
  "slug": "weekly-thing-220-ukraine-dao-nouns-icebergs",
  "description": "Ukraine DAO history, Kharkiv lives in ruin, billing systems nightmare, crypto crash post-mortem, DJI Mini 3 Pro, iPhone 13 Pro photography.",
  "image": "https://files.thingelstad.com/weekly-thing/2022/20220521.jpg",
  "publish_date": "2022-05-21T12:00:00Z",
  "absolute_url": "https://buttondown.com/weekly-thing/archive/weekly-thing-220-ukraine-dao-nouns-icebergs/"
}
