{
  "number": 134,
  "buttondown_id": "em_31jy9xr7d18jt9d3whsy3jfpf3",
  "subject": "Weekly Thing #134 / Platform & Product, Corporate Athlete, Mindfulness",
  "slug": "weekly-thing-134-platform-product-corporate",
  "description": "Platform-product fit, corporate athlete, full engagement, Amazon Dating, smart notes, paid membership, iOS 13.4, LEGO Masters, Luminary Loppet, mindfulness.",
  "image": "https://buttondown-attachments.s3.us-west-2.amazonaws.com/images/aeb245e9-099b-4a7e-8615-f71db03040fe.jpg",
  "publish_date": "2020-02-08T13:00:00Z",
  "absolute_url": "https://buttondown.com/weekly-thing/archive/weekly-thing-134-platform-product-corporate/"
}
