{
  "number": 157,
  "buttondown_id": "em_1gt52vtvr89q2sw8gngqq2dd0n",
  "subject": "Weekly Thing #157 / Superpower, Dune, Three Year Rule",
  "slug": "weekly-thing-157-superpower-dune-three-year-rule",
  "description": "Snowflake IPO, Apple One subscriptions, App Sprawl, Dune trailer, Ugh fields, Underwater datacenters, Brandi Carlile, Wikipedia Widgets.",
  "image": "https://files.thingelstad.com/weekly-thing/2020/20200919.jpg",
  "publish_date": "2020-09-19T12:00:00Z",
  "absolute_url": "https://buttondown.com/weekly-thing/archive/weekly-thing-157-superpower-dune-three-year-rule/"
}
