{
  "number": 103,
  "buttondown_id": "em_19mcwfbtcs9d39c13exjv1tbh2",
  "subject": "Weekly Thing #103 / Apr 27, 2019",
  "slug": "weekly-thing-103-apr-27-2019",
  "description": "Boeing 737 Max software, Tesla Full Self Driving ASIC, SpaceX Falcon Heavy launch, Mueller Report PDF, industrial strength WiFi.",
  "image": "https://files.thingelstad.com/weekly-thing/103/cover.jpg",
  "publish_date": "2019-04-27T12:00:00Z",
  "absolute_url": "https://buttondown.com/weekly-thing/archive/weekly-thing-103-apr-27-2019/"
}
